odoo/addons/account_invoice_line_sequence/README.rst
odoo/addons/account_invoice_line_sequence/__init__.py
odoo/addons/account_invoice_line_sequence/__manifest__.py
odoo/addons/account_invoice_line_sequence/init_hooks.py
odoo/addons/account_invoice_line_sequence/i18n/account_invoice_line_sequence.pot
odoo/addons/account_invoice_line_sequence/i18n/ar.po
odoo/addons/account_invoice_line_sequence/i18n/bg.po
odoo/addons/account_invoice_line_sequence/i18n/bs.po
odoo/addons/account_invoice_line_sequence/i18n/ca.po
odoo/addons/account_invoice_line_sequence/i18n/cs.po
odoo/addons/account_invoice_line_sequence/i18n/de.po
odoo/addons/account_invoice_line_sequence/i18n/el_GR.po
odoo/addons/account_invoice_line_sequence/i18n/en_GB.po
odoo/addons/account_invoice_line_sequence/i18n/es.po
odoo/addons/account_invoice_line_sequence/i18n/es_CR.po
odoo/addons/account_invoice_line_sequence/i18n/es_EC.po
odoo/addons/account_invoice_line_sequence/i18n/es_ES.po
odoo/addons/account_invoice_line_sequence/i18n/es_MX.po
odoo/addons/account_invoice_line_sequence/i18n/es_PE.po
odoo/addons/account_invoice_line_sequence/i18n/et.po
odoo/addons/account_invoice_line_sequence/i18n/fi.po
odoo/addons/account_invoice_line_sequence/i18n/fr.po
odoo/addons/account_invoice_line_sequence/i18n/fr_CA.po
odoo/addons/account_invoice_line_sequence/i18n/fr_CH.po
odoo/addons/account_invoice_line_sequence/i18n/gl.po
odoo/addons/account_invoice_line_sequence/i18n/hr.po
odoo/addons/account_invoice_line_sequence/i18n/hr_HR.po
odoo/addons/account_invoice_line_sequence/i18n/hu.po
odoo/addons/account_invoice_line_sequence/i18n/id.po
odoo/addons/account_invoice_line_sequence/i18n/it.po
odoo/addons/account_invoice_line_sequence/i18n/ja.po
odoo/addons/account_invoice_line_sequence/i18n/lt.po
odoo/addons/account_invoice_line_sequence/i18n/mk.po
odoo/addons/account_invoice_line_sequence/i18n/mn.po
odoo/addons/account_invoice_line_sequence/i18n/nb.po
odoo/addons/account_invoice_line_sequence/i18n/nb_NO.po
odoo11_addon_account_invoice_line_sequence-11.0.1.0.0.99.dev3.dist-info/METADATA
odoo11_addon_account_invoice_line_sequence-11.0.1.0.0.99.dev3.dist-info/WHEEL
odoo11_addon_account_invoice_line_sequence-11.0.1.0.0.99.dev3.dist-info/top_level.txt
odoo11_addon_account_invoice_line_sequence-11.0.1.0.0.99.dev3.dist-info/RECORD
